{
  "objects": {
    "alloc_counts": {
      "TaskRef": 828605,
      "Event": 402992,
      "StatusListener": 147271,
      "SysCallCondition": 138821,
      "Packet": 113405,
      "Timer": 85776,
      "LegacyDescriptor": 61421,
      "RegularFile": 59158,
      "Payload": 41956,
      "TCP": 2180,
      "TcpSocket": 2180,
      "Futex": 943,
      "Epoll": 68,
      "ManagedThread": 52,
      "SysCallHandler": 52,
      "NetworkInterface": 18,
      "FutexTable": 9,
      "Router": 9,
      "TimerFd": 8,
      "UDP": 7
    },
    "dealloc_counts": {
      "TaskRef": 828605,
      "Event": 402992,
      "StatusListener": 147271,
      "SysCallCondition": 138821,
      "Packet": 113405,
      "Timer": 85776,
      "LegacyDescriptor": 61421,
      "RegularFile": 59158,
      "Payload": 41956,
      "TCP": 2180,
      "TcpSocket": 2180,
      "Futex": 943,
      "Epoll": 68,
      "ManagedThread": 52,
      "SysCallHandler": 52,
      "NetworkInterface": 18,
      "FutexTable": 9,
      "Router": 9,
      "TimerFd": 8,
      "UDP": 7
    }
  },
  "syscalls": {
    "write": 381800,
    "epoll_wait": 159976,
    "read": 72626,
    "close": 61037,
    "open": 58854,
    "epoll_ctl": 58074,
    "mmap": 54472,
    "munmap": 54280,
    "fstat": 54148,
    "getrandom": 50942,
    "recvfrom": 49215,
    "sendto": 24977,
    "getsockopt": 6617,
    "poll": 6219,
    "ioctl": 5917,
    "getpid": 5453,
    "futex": 5051,
    "clock_gettime": 2671,
    "setsockopt": 2152,
    "socket": 1116,
    "connect": 1084,
    "accept4": 1078,
    "lseek": 973,
    "openat": 250,
    "rt_sigaction": 243,
    "brk": 192,
    "mprotect": 140,
    "fcntl": 99,
    "getdents64": 84,
    "shadow_hostname_to_addr_ipv4": 49,
    "getsockname": 37,
    "clone": 34,
    "set_robust_list": 34,
    "shadow_get_shm_blk": 34,
    "uname": 27,
    "bind": 24,
    "listen": 24,
    "gettid": 22,
    "shutdown": 20,
    "select": 19,
    "shadow_init_memory_manager": 18,
    "rt_sigprocmask": 14,
    "sysinfo": 10,
    "epoll_create": 8,
    "epoll_create1": 8,
    "flock": 8,
    "pipe2": 8,
    "timerfd_create": 8,
    "timerfd_settime": 8,
    "eventfd2": 7,
    "dup": 6,
    "sigaltstack": 4,
    "exit_group": 1,
    "fchmod": 1
  }
}